rupython/__main__.py
rupython/__Заголовочный_код__.py
rupython/__Общие_функции__.py
rupython/Преобразователь.py
rupython/Модули/Асинхр.py
rupython/Модули/Асинхронность.py
rupython/Модули/БД.py
rupython/Модули/ДатаВремя.py
rupython/Модули/Запросы.py
rupython/Модули/Коллекции.py
rupython/Модули/Куча.py
rupython/Модули/Матем.py
rupython/Модули/Очередь.py
rupython/Модули/Потоки.py
rupython/Модули/РегВыр.py
rupython/Модули/Случ.py
rupython/Модули/Файлы.py
rupython-1.4.0.dist-info/LICENSE
rupython-1.4.0.dist-info/METADATA
rupython-1.4.0.dist-info/WHEEL
rupython-1.4.0.dist-info/top_level.txt
rupython-1.4.0.dist-info/RECORD
