Metadata-Version: 2.1
Name: rupython
Version: 1.4.0
Summary: Исполнитель кода Русского Питона
Home-page: https://gitflic.ru/project/russky/rupython
Author: Сообщество русских программистов
License: ОДРН
Keywords: Россия,русский язык
Classifier: Programming Language :: Python :: 3
Classifier: Operating System :: OS Independent
Classifier: Topic :: Software Development
Classifier: Natural Language :: Russian
Requires-Python: >=3.8
License-File: LICENSE
